{
  "destinations": [
    {
      "title": "Las Vegas",
      "airportCode": "LAS",
      "youtubeId": "gasI6cyjkvM",
      "youtubeURL": "http://bit.ly/1Stlf6S"
    },
    {
      "title": "Seattle",
      "airportCode": "SEA",
      "youtubeId": "92ISlO9U-84",
      "youtubeURL": "http://bit.ly/1XDxOhs"
    },
    {
      "title": "Los Angeles",
      "airportCode": "LAX",
      "youtubeId": "bTvr_2v-0HI",
      "youtubeURL": "http://bit.ly/1Oskig5"
    },
    {
      "title": "Chicago",
      "airportCode": "CHI",
      "youtubeId": "QSwvg9Rv2EI",
      "youtubeURL": "http://bit.ly/1TpW4TK"
    },
    {
      "title": "New York",
      "airportCode": "JFK",
      "youtubeId": "MtCMtC50gwY",
      "youtubeURL": "http://bit.ly/1NjYCgN"
    },
    {
      "title": "San Francisco",
      "airportCode": "SFO",
      "youtubeId": "Oo6iAxf4si0",
      "youtubeURL": "http://bit.ly/1NF5gog"
    },
    {
      "title": "Boston",
      "airportCode": "BOS",
      "youtubeId": "e5cm2SDuHxA",
      "youtubeURL": "http://bit.ly/1QQW68A"
    },
    {
      "title": "San Diego",
      "airportCode": "SAN",
      "youtubeId": "-KMZW_zwRfc",
      "youtubeURL": "http://bit.ly/1Oskr31"
    },
    {
      "title": "Toronto",
      "airportCode": "YYZ",
      "youtubeId": "7uY0Ab5HlZ0",
      "youtubeURL": "http://bit.ly/1NZBRPQ"
    },
    {
      "title": "Atlanta",
      "airportCode": "ATL",
      "youtubeId": "iB4XbL_PmzQ",
      "youtubeURL": "http://bit.ly/1NmUalX"
    },
    {
      "title": "Orlando",
      "airportCode": "MCO",
      "youtubeId": "LfCsOwMc3hk",
      "youtubeURL": "http://bit.ly/1QakyjL"
    },
    {
      "title": "Honolulu",
      "airportCode": "HNL",
      "youtubeId": "aH--sKPgbSE",
      "youtubeURL": "http://bit.ly/1N0Hspk"
    },
    {
      "title": "St Petersburg",
      "airportCode": "PIE",
      "youtubeId": "N3ISUUO0CSo",
      "youtubeURL": "http://bit.ly/1NmUcKo"
    },
    {
      "title": "Washington DC",
      "airportCode": "WAS",
      "youtubeId": "7dilTLvbHxc",
      "youtubeURL": "http://bit.ly/1YEORSK"
    },
    {
      "title": "Miami",
      "airportCode": "MIA",
      "youtubeId": "58iT2L4VQj4",
      "youtubeURL": "http://bit.ly/1lrqOI8"
    },
    {
      "title": "Houston",
      "airportCode": "HOU",
      "youtubeId": "p9jWxwpXMPM",
      "youtubeURL": "http://bit.ly/1l4gtT2"
    },
    {
      "title": "Ottawa",
      "airportCode": "YOW",
      "youtubeId": "DtW0VqNkM9U",
      "youtubeURL": "https://r3---sn-n2gpou-nx5e.googlevideo.com/videoplayback?upn=zNSTpAAPtXM&sparams=dur%2Cid%2Cinitcwndbps%2Cip%2Cipbits%2Citag%2Clmt%2Cmime%2Cmm%2Cmn%2Cms%2Cmv%2Cpl%2Cratebypass%2Crequiressl%2Csource%2Cupn%2Cexpire&source=youtube&initcwndbps=7286250&pl=21&requiressl=yes&ratebypass=yes&key=yt6&ipbits=0&mime=video%2Fmp4&mm=31&signature=067B37173056F104F1F402A720D145E0D9F76CC3.78424CE57087138E044ADBEA6DDF8FA87BCF7ABC&mn=sn-n2gpou-nx5e&itag=22&mt=1448935777&mv=m&ms=au&sver=3&fexp=9408710%2C9416126%2C9417683%2C9420452%2C9422596%2C9422618%2C9423662&dur=254.049&ip=208.95.100.4&lmt=1447146292904959&id=o-AAW1IPQNGCkgQUlDzNvdRPsLn9so5SotilE8dS0-XWHz&expire=1448957438"
    },
    {
      "title": "Quebec",
      "airportCode": "YQB",
      "youtubeId": "XXhmblzSAeU",
      "youtubeURL": "https://r4---sn-n2gpou-nx5e.googlevideo.com/videoplayback?lmt=1399816671975426&dur=293.453&source=youtube&requiressl=yes&signature=7DB084DFF7BB3DE3D5411C32E3E893CD67B65D86.A517A2C84368CCFF5E61BEDDEB6050646153095A&key=yt6&fexp=9408492%2C9408710%2C9409128%2C9412777%2C9416126%2C9416481%2C9417683%2C9418203%2C9419451%2C9420452%2C9422541%2C9422596%2C9422618%2C9422967%2C9423421%2C9423662%2C9423715%2C9423978%2C9424965&mime=video%2Fmp4&sparams=dur%2Cid%2Cinitcwndbps%2Cip%2Cipbits%2Citag%2Clmt%2Cmime%2Cmm%2Cmn%2Cms%2Cmv%2Cpl%2Cratebypass%2Crequiressl%2Csource%2Cupn%2Cexpire&initcwndbps=6571250&ipbits=0&ms=au&mv=m&mt=1448935875&pl=21&ip=208.95.100.4&id=o-AKlNzL8sr0hcC4FiFwA3iY3vAz6LaxRTVOcl3gDIECQd&mn=sn-n2gpou-nx5e&mm=31&itag=22&sver=3&expire=1448957569&upn=matGpN43n98&ratebypass=yes"
    },
    {
      "title": "Denver",
      "airportCode": "DEN",
      "youtubeId": "VFPckJkcaPk",
      "youtubeURL": "https://r3---sn-n2gpou-nx5e.googlevideo.com/videoplayback?fexp=9408710%2C9416126%2C9417683%2C9420452%2C9422596%2C9422618%2C9423662&sparams=dur%2Cid%2Cinitcwndbps%2Cip%2Cipbits%2Citag%2Clmt%2Cmime%2Cmm%2Cmn%2Cms%2Cmv%2Cpl%2Cratebypass%2Crequiressl%2Csource%2Cupn%2Cexpire&expire=1448957629&itag=22&mime=video%2Fmp4&source=youtube&ms=au&mv=m&mt=1448935976&lmt=1407406875475368&dur=363.624&mn=sn-n2gpou-nx5e&mm=31&upn=Yb09EwlngJU&id=o-AIC8sAJ4zI5WYjeRw8Svh-vAKHpIl_ibqZthxfutL5Xa&ipbits=0&ip=208.95.100.4&key=yt6&pl=21&requiressl=yes&sver=3&signature=B0EA6DB28650D0D32D562FFA66042976D094C488.255330ECD73C9F92A31D4DED231315615294662E&ratebypass=yes&initcwndbps=6571250"
    },
    {
      "title": "Dallas",
      "airportCode": "DFW",
      "youtubeId": "Kt7lpqdbNgA",
      "youtubeURL": "https://r3---sn-n2gpou-nx5e.googlevideo.com/videoplayback?itag=22&ipbits=0&sver=3&lmt=1417273128503318&expire=1448957670&key=yt6&mime=video%2Fmp4&upn=EAAPA8Z72nI&mn=sn-n2gpou-nx5e&mm=31&mv=m&mt=1448935976&ms=au&signature=A8C441EC10B51F0B5D9281D785AF22355C0B9086.372A112415C0936CBBD40654AB02E0CF7D65E3F7&sparams=dur%2Cid%2Cinitcwndbps%2Cip%2Cipbits%2Citag%2Clmt%2Cmime%2Cmm%2Cmn%2Cms%2Cmv%2Cpl%2Cratebypass%2Crequiressl%2Csource%2Cupn%2Cexpire&fexp=9408501%2C9408710%2C9409126%2C9416126%2C9417259%2C9417683%2C9418201%2C9418203%2C9418400%2C9418749%2C9420452%2C9421411%2C9421749%2C9422501%2C9422596%2C9422618%2C9423589%2C9423662%2C9424082%2C9424646%2C9424965%2C9425208%2C9425230&ip=208.95.100.4&id=o-ABjYlTfN9eYDNtORkKPPaAbaYC0Z1Sz9cPHNVDIpgxM5&requiressl=yes&ratebypass=yes&source=youtube&dur=292.060&pl=21&initcwndbps=6571250"
    },
    {
      "title": "Portland",
      "airportCode": "PDX",
      "youtubeId": "1PGiixdhNVk",
      "youtubeURL": "https://r3---sn-n2gpou-nx5e.googlevideo.com/videoplayback?id=o-ABeSm3Gzvf2ZpZa4h-SKBjTm2VYw1OX6AvGWQ9iT3fnn&signature=63E0EC9A108154F3B5CAA2CFF060EE319D104600.CF51192112953776DDFAA6AA97BBA67CFA68946E&ms=au&mt=1448936078&upn=M-nhR2rtcsk&mv=m&pl=21&itag=22&mm=31&ip=208.95.100.4&mn=sn-n2gpou-nx5e&key=yt6&mime=video%2Fmp4&fexp=9407116%2C9408502%2C9408710%2C9413010%2C9413122%2C9413141%2C9416126%2C9417683%2C9418751%2C9420452%2C9422596%2C9422618%2C9422673%2C9423485%2C9423662%2C9423785%2C9423821%2C9424965%2C9425308&dur=312.656&ratebypass=yes&sver=3&requiressl=yes&source=youtube&initcwndbps=4806250&ipbits=0&expire=1448957726&sparams=dur%2Cid%2Cinitcwndbps%2Cip%2Cipbits%2Citag%2Clmt%2Cmime%2Cmm%2Cmn%2Cms%2Cmv%2Cpl%2Cratebypass%2Crequiressl%2Csource%2Cupn%2Cexpire&lmt=1388266850160925"
    },
    {
      "title": "New Orleans",
      "airportCode": "MSY",
      "youtubeId": "sQRNkpGkT2Y",
      "youtubeURL": "https://r4---sn-n2gpou-nx5e.googlevideo.com/videoplayback?requiressl=yes&sver=3&upn=JDzurkpPy0g&expire=1448957776&lmt=1408592104812871&key=yt6&mime=video%2Fmp4&pl=21&source=youtube&signature=89B47CBFA81442AE96AABDF5E06E73563C038CA6.1AD5C760DE8C15543EAB40B6EA2DAEAEBFE11064&ratebypass=yes&sparams=dur%2Cid%2Cinitcwndbps%2Cip%2Cipbits%2Citag%2Clmt%2Cmime%2Cmm%2Cmn%2Cms%2Cmv%2Cpl%2Cratebypass%2Crequiressl%2Csource%2Cupn%2Cexpire&itag=22&id=o-AOy0yUhiAudLmtK2QRAkz05kEtleT0h_3JW8KCAm4cVE&mm=31&ipbits=0&mn=sn-n2gpou-nx5e&initcwndbps=4806250&fexp=9408710%2C9409126%2C9416126%2C9417683%2C9418145%2C9418184%2C9418203%2C9419452%2C9419548%2C9420452%2C9420718%2C9421165%2C9422401%2C9422579%2C9422596%2C9422618%2C9422797%2C9423662%2C9423940%2C9424319%2C9424964%2C9425227&ip=208.95.100.4&ms=au&mt=1448936078&dur=333.717&mv=m"
    },
    {
      "title": "Montreal",
      "airportCode": "YUL",
      "youtubeId": "poe2cLKw9ko",
      "youtubeURL": "https://r3---sn-n2gpou-nx5e.googlevideo.com/videoplayback?lmt=1427192589839060&sparams=dur%2Cid%2Cinitcwndbps%2Cip%2Cipbits%2Citag%2Clmt%2Cmime%2Cmm%2Cmn%2Cms%2Cmv%2Cpl%2Cratebypass%2Crequiressl%2Csource%2Cupn%2Cexpire&ipbits=0&requiressl=yes&initcwndbps=4806250&source=youtube&dur=335.760&sver=3&ratebypass=yes&fexp=9408710%2C9414929%2C9416126%2C9417683%2C9418400%2C9419294%2C9419446%2C9420452%2C9420772%2C9422596%2C9422618%2C9422843%2C9423292%2C9423428%2C9423633%2C9423662%2C9423853%2C9424378%2C9424489%2C9424902%2C9424966%2C9425307&key=yt6&mime=video%2Fmp4&expire=1448957829&mn=sn-n2gpou-nx5e&ip=208.95.100.4&mm=31&itag=22&pl=21&signature=711705A3FD786202796D493BD452373BA66E8993.435124991C357DDC01FC990A5522E93CCEA5EAEF&id=o-AEiTP_GIgLVft7n8wEdD46aAR3MZ211QpuLtPkoSEdxW&mv=m&upn=m-cMD6bdFxA&mt=1448936179&ms=au"
    },
    {
      "title": "San Antonio",
      "airportCode": "SAT",
      "youtubeId": "ifW6I46cIpk",
      "youtubeURL": "https://r3---sn-n2gpou-nx5e.googlevideo.com/videoplayback?ms=au&mv=m&mt=1448936179&expire=1448957877&sver=3&requiressl=yes&ipbits=0&mn=sn-n2gpou-nx5e&mm=31&id=o-AKFZJFDCXoMg7FdSCx8DbcpBFBbM8gpJJKRX5cKbyboW&itag=22&ip=208.95.100.4&key=yt6&dur=271.766&lmt=1448773687464036&fexp=9408710%2C9416126%2C9417683%2C9420452%2C9422596%2C9422618%2C9423662%2C9424364&source=youtube&upn=PwFzTORYrNs&mime=video%2Fmp4&sparams=dur%2Cid%2Cinitcwndbps%2Cip%2Cipbits%2Citag%2Clmt%2Cmime%2Cmm%2Cmn%2Cms%2Cmv%2Cpl%2Cratebypass%2Crequiressl%2Csource%2Cupn%2Cexpire&initcwndbps=4806250&ratebypass=yes&pl=21&signature=447DCCA60ECC04B25152A78D428C5898DC2EE264.C5A84DDE445DEAC9F72E4E443C167E069020F904"
    },
    {
      "title": "Austin",
      "airportCode": "AUS",
      "youtubeId": "AZwGHEYT5x8",
      "youtubeURL": "https://r3---sn-n2gpou-nx5e.googlevideo.com/videoplayback?id=o-APr3UuSCauJP8OtEImyc5cj4SxbZ9X_boL8bwG81vq70&signature=7D45E63BBB4EE1536674691BE92FBC0047914801.C644A13B33A124BC8D207B6883856C03A3F24CA2&ms=au&mt=1448936291&upn=UGSrlKgM2Ms&mv=m&pl=21&itag=22&mm=31&ip=208.95.100.4&mn=sn-n2gpou-nx5e&key=yt6&mime=video%2Fmp4&fexp=9405186%2C9408086%2C9408491%2C9408710%2C9416126%2C9417683%2C9420452%2C9421525%2C9422342%2C9422540%2C9422596%2C9422618%2C9423294%2C9423329%2C9423662%2C9424189%2C9424434%2C9424771%2C9424965&dur=260.063&ratebypass=yes&sver=3&requiressl=yes&source=youtube&initcwndbps=4806250&ipbits=0&expire=1448957924&sparams=dur%2Cid%2Cinitcwndbps%2Cip%2Cipbits%2Citag%2Clmt%2Cmime%2Cmm%2Cmn%2Cms%2Cmv%2Cpl%2Cratebypass%2Crequiressl%2Csource%2Cupn%2Cexpire&lmt=1431868963331021"
    },
    {
      "title": "Maui",
      "airportCode": "JHM",
      "youtubeId": "MEle9Vfxoh0",
      "youtubeURL": "https://r1---sn-n2gpou-nx5e.googlevideo.com/videoplayback?pl=21&mime=video%2Fmp4&source=youtube&key=yt6&sparams=dur%2Cid%2Cinitcwndbps%2Cip%2Cipbits%2Citag%2Clmt%2Cmime%2Cmm%2Cmn%2Cms%2Cmv%2Cpl%2Cratebypass%2Crequiressl%2Csource%2Cupn%2Cexpire&itag=22&signature=8C9DAA0733FB7C22BB3FD79A4593736F6D80142E.D1C5B9048E06EF0F469F42C1E0A9730D089DBF50&ratebypass=yes&ip=208.95.100.4&ms=au&dur=263.012&mv=m&mt=1448936291&id=o-AKfNxqWbATna8lp_Ircqpr1J0ECWwyba5T90fdXPjkl5&mn=sn-n2gpou-nx5e&mm=31&ipbits=0&initcwndbps=4806250&expire=1448957964&sver=3&requiressl=yes&upn=7egB8iKEoVM&lmt=1432551912185409&fexp=9408710%2C9416126%2C9417683%2C9420452%2C9422596%2C9422618%2C9423662"
    },
    {
      "title": "Philadelphia",
      "airportCode": "PHL",
      "youtubeId": "GHDtG4_Eq_c",
      "youtubeURL": "https://r1---sn-n2gpou-nx5e.googlevideo.com/videoplayback?id=o-AEsdpnUPU7bxF8Y78KMSO8TOEFPShLiK-BZYq2y4NW-P&source=youtube&initcwndbps=4806250&dur=292.362&expire=1448957999&key=yt6&ip=208.95.100.4&lmt=1435468110960418&sver=3&signature=49BAC661C4F9B1D0AD01E701DCB5CA442C4D89EB.D77898EA5C8FEF2489398866A47CA71EC8B92C40&upn=KqVRcoI8CGo&ipbits=0&sparams=dur%2Cid%2Cinitcwndbps%2Cip%2Cipbits%2Citag%2Clmt%2Cmime%2Cmm%2Cmn%2Cms%2Cmv%2Cpl%2Cratebypass%2Crequiressl%2Csource%2Cupn%2Cexpire&fexp=9408710%2C9413209%2C9413277%2C9416126%2C9416903%2C9417683%2C9420452%2C9420569%2C9420925%2C9421247%2C9421353%2C9422596%2C9422618%2C9423039%2C9423662%2C9423848%2C9424090%2C9424298%2C9424643%2C9424965&pl=21&itag=22&mime=video%2Fmp4&requiressl=yes&ms=au&mt=1448936291&mv=m&mm=31&mn=sn-n2gpou-nx5e&ratebypass=yes"
    },
    {
      "title": "Phoenix",
      "airportCode": "PHX",
      "youtubeId": "SAtEodJdK0k",
      "youtubeURL": "https://r3---sn-n2gpou-nx5e.googlevideo.com/videoplayback?ratebypass=yes&upn=A4__vZ4T4Kw&key=yt6&signature=5A44AF638BAAD4DD1E3E8D8F83CC6159B9782DA1.5A934E31F4F034901DA517D53F341B66F5ED4392&mime=video%2Fmp4&initcwndbps=4786250&sver=3&lmt=1433410739303831&expire=1448958039&ipbits=0&sparams=dur%2Cid%2Cinitcwndbps%2Cip%2Cipbits%2Citag%2Clmt%2Cmime%2Cmm%2Cmn%2Cms%2Cmv%2Cpl%2Cratebypass%2Crequiressl%2Csource%2Cupn%2Cexpire&dur=272.161&requiressl=yes&id=o-ALyrMZVoKRpd1q66Qr3HDRWuPZwmu1foIvCxpSvnlJot&pl=21&mn=sn-n2gpou-nx5e&mm=31&itag=22&ms=au&fexp=9408490%2C9408710%2C9415864%2C9416126%2C9416985%2C9417683%2C9418204%2C9419446%2C9420239%2C9420452%2C9420929%2C9422141%2C9422484%2C9422522%2C9422596%2C9422618%2C9422673%2C9422735%2C9423241%2C9423662%2C9424615%2C9424715%2C9424966&mv=m&mt=1448936391&source=youtube&ip=208.95.100.4"
    }
  ]
}
